{
    "version": "0.2",
    "language": "en",
    "dictionaries": [
        "node",
        "typescript",
        "companies",
        "softwareTerms",
        "misc",
        "npm",
        "git"
    ],
    "ignorePaths": [
        "**/.git/**",
        "**/node_modules/**",
        "**/.turbo/**",
        "**/build/**",
        "**/out/**",
        "**/dist/**",
        "**/.vscode/**",
        "**/*.tsbuildinfo",
        "**/bun.lockb",
        "**/*.svg"
    ],
    "languageSettings": [
        {
            "languageId": "commit-msg",
            "ignoreRegExpList": [
                "/^#.*/gm"
            ]
        }
    ],
    "words": [
        "kanbn",
        "lefthook"
    ]
}
